.gitignore
CHANGELOG
LICENSE
MANIFEST.in
README.md
get-pip.py
setup.py
.github/FUNDING.yml
.vscode/settings.json
node_modules/@babel/code-frame/LICENSE
node_modules/@babel/code-frame/README.md
node_modules/@babel/code-frame/package.json
node_modules/@babel/helper-validator-identifier/LICENSE
node_modules/@babel/helper-validator-identifier/README.md
node_modules/@babel/helper-validator-identifier/package.json
node_modules/@babel/highlight/LICENSE
node_modules/@babel/highlight/README.md
node_modules/@babel/highlight/package.json
node_modules/@babel/highlight/node_modules/chalk/package.json
node_modules/@babel/highlight/node_modules/chalk/readme.md
node_modules/@eslint/eslintrc/CHANGELOG.md
node_modules/@eslint/eslintrc/LICENSE
node_modules/@eslint/eslintrc/README.md
node_modules/@eslint/eslintrc/package.json
node_modules/@eslint/eslintrc/conf/category-list.json
node_modules/@eslint/eslintrc/conf/replacements.json
node_modules/@types/color-name/LICENSE
node_modules/@types/color-name/README.md
node_modules/@types/color-name/package.json
node_modules/acorn/CHANGELOG.md
node_modules/acorn/LICENSE
node_modules/acorn/README.md
node_modules/acorn/package.json
node_modules/acorn-jsx/LICENSE
node_modules/acorn-jsx/README.md
node_modules/acorn-jsx/package.json
node_modules/ajv/LICENSE
node_modules/ajv/README.md
node_modules/ajv/package.json
node_modules/ajv/lib/dotjs/README.md
node_modules/ajv/lib/refs/data.json
node_modules/ajv/lib/refs/json-schema-draft-04.json
node_modules/ajv/lib/refs/json-schema-draft-06.json
node_modules/ajv/lib/refs/json-schema-draft-07.json
node_modules/ajv/lib/refs/json-schema-secure.json
node_modules/ajv/scripts/.eslintrc.yml
node_modules/ansi-colors/LICENSE
node_modules/ansi-colors/README.md
node_modules/ansi-colors/package.json
node_modules/ansi-regex/package.json
node_modules/ansi-regex/readme.md
node_modules/ansi-styles/package.json
node_modules/ansi-styles/readme.md
node_modules/argparse/CHANGELOG.md
node_modules/argparse/LICENSE
spookvooperapi.egg-info/PKG-INFO
spookvooperapi.egg-info/SOURCES.txt
spookvooperapi.egg-info/dependency_links.txt
spookvooperapi.egg-info/top_level.txt