Metadata-Version: 2.1
Name: spookvooperapi
Version: 0.0.1
Summary: Allows for easy use of the spookvooper.com API
Home-page: https://bowlingbank.co
Author: Brendan Lane
Author-email: me@imbl.me
License: UNKNOWN
Keywords: spookvooper
Platform: UNKNOWN
Classifier: Development Status :: 3 - Alpha
Classifier: Intended Audience :: Developers
Classifier: License :: OSI Approved :: GNU General Public License v3 or later (GPLv3+)
Classifier: Natural Language :: English
Classifier: Programming Language :: Python :: 3
Classifier: Topic :: Software Development :: Libraries :: Python Modules
Requires-Python: >=3.6
